pyrathole-0.1.2.dist-info/METADATA
pyrathole-0.1.2.dist-info/WHEEL
pyrathole-0.1.2.dist-info/licenses/LICENSE
pyrathole/__init__.py
pyrathole/pyrathole.cpython-312-darwin.so
pyrathole-0.1.2.dist-info/RECORD
