Metadata-Version: 2.4
Name: pyrathole
Version: 0.1.2
Classifier: Development Status :: 3 - Alpha
Classifier: Intended Audience :: Developers
Classifier: License :: OSI Approved :: Apache Software License
Classifier: Programming Language :: Python :: 3
Classifier: Programming Language :: Python :: 3.8
Classifier: Programming Language :: Python :: 3.9
Classifier: Programming Language :: Python :: 3.10
Classifier: Programming Language :: Python :: 3.11
Classifier: Programming Language :: Python :: 3.12
Classifier: Programming Language :: Rust
Classifier: Topic :: Internet :: WWW/HTTP :: HTTP Servers
Classifier: Topic :: System :: Networking
License-File: LICENSE
Summary: Python bindings for rathole reverse tunneling proxy
Keywords: rathole,tunnel,proxy,networking
Home-Page: https://github.com/zZedix/PyRathole
Author-email: zZedix <your-email@example.com>
License: Apache-2.0
Requires-Python: >=3.8
Project-URL: Homepage, https://github.com/zZedix/PyRathole
Project-URL: Repository, https://github.com/zZedix/PyRathole
Project-URL: Issues, https://github.com/zZedix/PyRathole/issues
